voy/__init__.py
voy/cmd.py
voy/models.py
voy/query.py
voy/seed.py
voy/storage.py
voy/version.py
voy/views.py
voy/voy.py
voy/lib/__init__.py
voy/lib/tex2utf.py
voy-0.1.2.dist-info/licenses/LICENSE
voy-0.1.2.dist-info/METADATA
voy-0.1.2.dist-info/WHEEL
voy-0.1.2.dist-info/entry_points.txt
voy-0.1.2.dist-info/top_level.txt
voy-0.1.2.dist-info/RECORD
