Metadata-Version: 2.4
Name: voy
Version: 0.1.2
Summary: A CLI for following arXiv authors.
Author-email: Florin Gogianu <florin.gogianu@gmail.com>
License: MIT License
Project-URL: Homepage, https://github.com/floringogianu/voy
Keywords: arxiv,feed
Classifier: License :: OSI Approved :: MIT License
Classifier: Programming Language :: Python
Classifier: Programming Language :: Python :: 3
Requires-Python: >=3.12.0
License-File: LICENSE
Requires-Dist: arxiv>=2.1.0
Requires-Dist: colorful>=0.5.6
Requires-Dist: datargs>=1.1.0
Requires-Dist: jsonlines>=4.0.0
Requires-Dist: platformdirs>=4.1.0
Requires-Dist: xxhash>=3.4.1
Requires-Dist: windows-curses>=2.3.2; sys_platform == "win32"
Dynamic: license-file
